simple_track_builder/__init__.py
simple_track_builder/_simple_track_builder.py
simple_track_builder/_tests/__init__.py
simple_track_builder/_tests/test_module.py
Simple_Track_Builder-0.0.2.dist-info/LICENSE
Simple_Track_Builder-0.0.2.dist-info/METADATA
Simple_Track_Builder-0.0.2.dist-info/WHEEL
Simple_Track_Builder-0.0.2.dist-info/entry_points.txt
Simple_Track_Builder-0.0.2.dist-info/top_level.txt
Simple_Track_Builder-0.0.2.dist-info/RECORD
