Metadata-Version: 2.1
Name: Simple-Track-Builder
Version: 0.0.2
Summary: A very simple cell tracker from labeled images
Home-page: https://github.com/GuignardLab/Simple-Track-Builder
Author: Léo Guignard
Author-email: léo.guignard@univ-amu.fr
License: MIT
Project-URL: Bug Tracker, https://github.com/GuignardLab/Simple-Track-Builder/issues
Project-URL: Documentation, https://github.com/GuignardLab/Simple-Track-Builder#README.md
Project-URL: Source Code, https://github.com/GuignardLab/Simple-Track-Builder
Project-URL: User Support, https://github.com/GuignardLab/Simple-Track-Builder/issues
Classifier: Development Status :: 2 - Pre-Alpha
Classifier: Intended Audience :: Developers
Classifier: License :: OSI Approved :: MIT License
Classifier: Operating System :: OS Independent
Classifier: Programming Language :: Python
Classifier: Programming Language :: Python :: 3
Classifier: Programming Language :: Python :: 3 :: Only
Classifier: Programming Language :: Python :: 3.8
Classifier: Programming Language :: Python :: 3.9
Classifier: Programming Language :: Python :: 3.10
Classifier: Topic :: Scientific/Engineering :: Image Processing
Requires-Python: >=3.8
License-File: LICENSE
Requires-Dist: numpy
Requires-Dist: scipy
Requires-Dist: bumpver
Requires-Dist: LineageTree >=1.4.2
Requires-Dist: tifffile
Provides-Extra: testing
Requires-Dist: tox ; extra == 'testing'
Requires-Dist: pytest ; extra == 'testing'
Requires-Dist: pytest-cov ; extra == 'testing'
